{"cameraMode":{"drawMode":0,"name":"Shaded","section":"Shading Mode"},"sceneLighting":true,"audioPlay":false,"sceneViewState":{"showFog":true,"showMaterialUpdate":false,"showSkybox":true,"showFlares":true,"showImageEffects":true,"showParticleSystems":true},"in2DMode":false,"pivot":{"x":-11.05177116394043,"y":-11.697568893432618,"z":55.40700912475586},"rotation":{"x":-0.16751518845558167,"y":0.005025080870836973,"z":-0.0008539306581951678,"w":-0.9858608841896057},"size":112.10554504394531,"orthographic":false}